CHANGES.rst
LICENCE
MANIFEST.in
README.rst
bootstrap.py
dev-requirements.txt
pavement.py
paver-minilib.zip
setup.cfg
setup.py
docs/source/changes.rst
docs/source/conf.py
docs/source/index.rst
docs/source/license.rst
src/paver_templates.egg-info/PKG-INFO
src/paver_templates.egg-info/SOURCES.txt
src/paver_templates.egg-info/dependency_links.txt
src/paver_templates.egg-info/entry_points.txt
src/paver_templates.egg-info/not-zip-safe
src/paver_templates.egg-info/requires.txt
src/paver_templates.egg-info/top_level.txt
src/pavertemplates/__init__.py
src/pavertemplates/paster-templates/licenses/agpl.txt
src/pavertemplates/paster-templates/licenses/gpl-2.0.txt
src/pavertemplates/paster-templates/licenses/gpl.txt
src/pavertemplates/paster-templates/licenses/lgpl-2.1.txt
src/pavertemplates/paster-templates/licenses/lgpl.txt
src/pavertemplates/paster-templates/paver_package/LICENSE.txt_tmpl
src/pavertemplates/paster-templates/paver_package/MANIFEST.in
src/pavertemplates/paster-templates/paver_package/README.rst_tmpl
src/pavertemplates/paster-templates/paver_package/pavement.py_tmpl
src/pavertemplates/paster-templates/paver_package/+package+/__init__.py_tmpl
src/pavertemplates/paster-templates/paver_package/docs/conf.py_tmpl
src/pavertemplates/paster-templates/paver_package/docs/index.rst_tmpl
support-files/readme.rst