Metadata-Version: 1.0
Name: paver-templates
Version: 0.1.0b3
Summary: Paver-enable template
Home-page: http://dinoboff.github.com/paver-templates
Author: Damien Lebrun
Author-email: dinoboff@hotmail.com
License: BSD
Keywords: Paver PasteScript template
Platform: UNKNOWN
Classifier: Development Status :: 4 - Beta
Classifier: Programming Language :: Python :: 2.4
Classifier: Programming Language :: Python :: 2.5
Classifier: Programming Language :: Python :: 2.6
Classifier: Environment :: Console
Classifier: Intended Audience :: Developers
Classifier: License :: OSI Approved :: BSD License
Classifier: Operating System :: OS Independent
Classifier: Topic :: Software Development :: Libraries :: Python Modules
